moyalstar/__init__.py
moyalstar/core/__init__.py
moyalstar/core/base.py
moyalstar/core/eom.py
moyalstar/core/hilbert_operators.py
moyalstar/core/scalars.py
moyalstar/core/star_product.py
moyalstar/core/weyl_transform.py
moyalstar/core/wigner_transform.py
moyalstar/testing/test_all.py
moyalstar/utils/__init__.py
moyalstar/utils/grouping.py
moyalstar/utils/multiprocessing.py
moyalstar-1.1.0.dist-info/licenses/LICENSE
moyalstar-1.1.0.dist-info/METADATA
moyalstar-1.1.0.dist-info/WHEEL
moyalstar-1.1.0.dist-info/top_level.txt
moyalstar-1.1.0.dist-info/RECORD
