Metadata-Version: 2.4
Name: moyalstar
Version: 1.1.0
Summary: A Moyal star-product calculator for the quantum phase space formalism
Author-email: Hendry Minfui Lim <hendry01@ui.ac.id>
License:                     GNU GENERAL PUBLIC LICENSE
Project-URL: Repository, https://github.com/hendry24/moyalstar
Project-URL: Issues, https://github.com/hendry24/moyalstar/issues
Keywords: Moyal star-product,Wigner transform,Quantum phase space
Classifier: Development Status :: 5 - Production/Stable
Classifier: Intended Audience :: Science/Research
Classifier: License :: OSI Approved :: GNU General Public License v3 (GPLv3)
Requires-Python: >=3.8
License-File: LICENSE
Requires-Dist: sympy>=1.13.3
Requires-Dist: dill
Dynamic: license-file
